spark_roomba/cli.py
spark_roomba/create.py
spark_roomba-0.1.1.dist-info/METADATA
spark_roomba-0.1.1.dist-info/WHEEL
spark_roomba-0.1.1.dist-info/entry_points.txt
spark_roomba-0.1.1.dist-info/RECORD
