Metadata-Version: 2.1
Name: spark-roomba
Version: 0.1.1
Summary: A CLI tool to control Roomba
License: MIT
Author: Maki
Author-email: sunwood.ai.labs@gmail.com
Requires-Python: >=3.10,<4.0
Classifier: License :: OSI Approved :: MIT License
Classifier: Programming Language :: Python :: 3
Classifier: Programming Language :: Python :: 3.10
Classifier: Programming Language :: Python :: 3.11
Classifier: Programming Language :: Python :: 3.12
Requires-Dist: loguru (>=0.6.0,<0.7.0)
Requires-Dist: open-interpreter (>=0.1.0,<0.2.0)
Requires-Dist: pyserial (>=3.5,<4.0)
Requires-Dist: python-dotenv (>=0.19.0,<0.20.0)
Project-URL: Bug Tracker, https://github.com/Sunwood-ai-labs/SPARK/issues
Project-URL: Homepage, https://github.com/Sunwood-ai-labs/SPARK
